{
  "available_tasks": [
    "TASK_START"
  ],
  "custom": false,
  "documentation_url": "https://www.instill.tech/docs/latest/vdp/operators/op-start",
  "icon": "assets/start.svg",
  "icon_url": "",
  "id": "start",
  "public": true,
  "spec": {},
  "title": "Start",
  "tombstone": false,
  "uid": "2ac8be70-0f7a-4b61-a33d-098b8acfa6f3",
  "version": "0.1.0",
  "source_url": "https://github.com/instill-ai/component/blob/main/pkg/operator/start/v0",
  "description": "Define data formats customized for their AI-first applications",
  "release_stage": "RELEASE_STAGE_ALPHA"
}
